<?xml version="1.0" encoding="utf-8" ?>
<dwsync>
<file name="app.js" server="C:/xampp/htdocs/dvi_kenya/" local="130389187640000000" remote="130389187640000000" />
<file name="canvas-to-blob.min.js" server="C:/xampp/htdocs/dvi_kenya/" local="130416049860000000" remote="130416049860000000" />
<file name="jquery.blueimp-gallery.min.js" server="C:/xampp/htdocs/dvi_kenya/" local="130416057360000000" remote="130416057360000000" />
<file name="jquery.fileupload-angular.js" server="C:/xampp/htdocs/dvi_kenya/" local="130389187640000000" remote="130389187640000000" />
<file name="jquery.fileupload-audio.js" server="C:/xampp/htdocs/dvi_kenya/" local="130389187640000000" remote="130389187640000000" />
<file name="jquery.fileupload-image.js" server="C:/xampp/htdocs/dvi_kenya/" local="130416042040000000" remote="130416042040000000" />
<file name="jquery.fileupload-jquery-ui.js" server="C:/xampp/htdocs/dvi_kenya/" local="130389187640000000" remote="130389187640000000" />
<file name="jquery.fileupload-process.js" server="C:/xampp/htdocs/dvi_kenya/" local="130389187640000000" remote="130389187640000000" />
<file name="jquery.fileupload-ui.js" server="C:/xampp/htdocs/dvi_kenya/" local="130389187640000000" remote="130389187640000000" />
<file name="jquery.fileupload-validate.js" server="C:/xampp/htdocs/dvi_kenya/" local="130389187640000000" remote="130389187640000000" />
<file name="jquery.fileupload-video.js" server="C:/xampp/htdocs/dvi_kenya/" local="130389187640000000" remote="130389187640000000" />
<file name="jquery.fileupload.js" server="C:/xampp/htdocs/dvi_kenya/" local="130389187640000000" remote="130389187640000000" />
<file name="jquery.iframe-transport.js" server="C:/xampp/htdocs/dvi_kenya/" local="130389187640000000" remote="130389187640000000" />
<file name="load-image.min.js" server="C:/xampp/htdocs/dvi_kenya/" local="130416049680000000" remote="130416049680000000" />
<file name="main.js" server="C:/xampp/htdocs/dvi_kenya/" local="130416081760000000" remote="130416081760000000" />
<file name="tmpl.min.js" server="C:/xampp/htdocs/dvi_kenya/" local="130416049460000000" remote="130416049460000000" />
</dwsync>